LICENSE
README.md
setup.py
najapy/__init__.py
najapy.egg-info/PKG-INFO
najapy.egg-info/SOURCES.txt
najapy.egg-info/dependency_links.txt
najapy.egg-info/requires.txt
najapy.egg-info/top_level.txt
najapy/asyncio/__init__.py
najapy/asyncio/future.py
najapy/cache/__init__.py
najapy/cache/base.py
najapy/cache/redis.py
najapy/common/__init__.py
najapy/common/async_base.py
najapy/common/base.py
najapy/common/buffer.py
najapy/common/error.py
najapy/common/excel.py
najapy/common/interface.py
najapy/common/metaclass.py
najapy/common/pool.py
najapy/common/process.py
najapy/common/struct.py
najapy/common/task.py
najapy/database/__init__.py
najapy/database/mongo.py
najapy/database/mysql.py
najapy/enum/__init__.py
najapy/enum/base_enum.py
najapy/event/__init__.py
najapy/event/async_event.py
najapy/event/event.py
najapy/frame/__init__.py
najapy/frame/logging.py
najapy/frame/fastapi/__init__.py
najapy/frame/fastapi/base.py
najapy/frame/fastapi/form.py
najapy/frame/fastapi/response.py
najapy/frame/fastapi/ws.py
najapy/middleware/__init__.py
najapy/middleware/rabbitmq/__init__.py
najapy/middleware/rabbitmq/consumer.py
najapy/middleware/rabbitmq/producer.py
najapy/middleware/rabbitmq/producer_pool.py
najapy/net/__init__.py
najapy/net/http.py
najapy/scaffold/__init__.py
najapy/scaffold/fastapi_example_project/__init__.py
najapy/scaffold/fastapi_example_project/manage.py
najapy/scaffold/fastapi_example_project/fastapi_example/__init__.py
najapy/scaffold/fastapi_example_project/fastapi_example/activate.py
najapy/scaffold/fastapi_example_project/fastapi_example/err_handler.py
najapy/scaffold/fastapi_example_project/fastapi_example/main.py
najapy/scaffold/fastapi_example_project/fastapi_example/router.py
najapy/scaffold/fastapi_example_project/fastapi_example/abc_base/__init__.py
najapy/scaffold/fastapi_example_project/fastapi_example/abc_base/model/__init__.py
najapy/scaffold/fastapi_example_project/fastapi_example/abc_base/model/base_model.py
najapy/scaffold/fastapi_example_project/fastapi_example/abc_base/service/__init__.py
najapy/scaffold/fastapi_example_project/fastapi_example/abc_base/service/base_service.py
