Metadata-Version: 2.1
Name: najapy
Version: 1.3.2
Summary: Async Suite For Python
Home-page: https://github.com/lanqiao-dev/najapy.git
Author: lanqiao
Author-email: 
License: Apache License Version 2.0
Platform: all
Classifier: Programming Language :: Python :: 3.8
Classifier: License :: OSI Approved :: Apache Software License
Classifier: Operating System :: POSIX :: Linux
Requires-Python: >= 3.8
License-File: LICENSE
